FPGA/first_assignment/ALU.v
module eight_bit_alu(
    input [7:0] a,b,
    input [2:0] sel,
    output [7:0] o,
    output c
);

wire [8:0] sum;

assign sum = (sel == 3'b001) ? a-b : a+b;

assign o =  (sel == 3'b000) ? a+b :
            (sel == 3'b001) ? a-b :
            (sel == 3'b010) ? a&b :
            (sel == 3'b011) ? a|b : 
            (sel == 3'b100) ? a^b : 
            (sel == 3'b101) ? ~a : 
            (sel == 3'b110) ? a<<1 :
             b>>1;

assign c = (sel == 3'b000 || sel == 3'b001) ? sum[8] : 1'b0;
endmodule

FPGA/first_assignment/alu_tb.v
`timescale 1ns/1ps

module eight_bit_alu_tb;
reg [7:0]a,b;
reg [2:0]sel;
wire [7:0]o;
wire c;
eight_bit_alu out(
    .a(a),
    .b(b),
    .sel(sel),
    .o(o),
    .c(c)
);
initial begin

    $monitor("a=%H b=%H o=%H c=%b",a,b,o,c);

    $dumpfile("eight_bit_tb.vcd");
    $dumpvars(0,out);

    a=8'HFF;b=8'HF0;sel=3'b000; #100;
    a=8'H0A;b=8'HF0;sel=3'b001; #100;
    a=8'H8D;b=8'HF0;sel=3'b010;  #100;
    a=8'H3E;b=8'HF0;sel=3'b011;  #100;
    a=8'H3E;b=8'HF0;sel=3'b100;  #100;
    a=8'H3E;b=8'HF0;sel=3'b101;  #100;
    a=8'H3E;b=8'HF0;sel=3'b110;  #100;
    a=8'H3E;b=8'HF0;sel=3'b111;  #100;
    $finish;    
end
endmodule

FPGA/first_assignment/eight_bit_tb.vcd
$date
	Thu Jun 25 20:21:38 2026
$end
$version
	Icarus Verilog
$end
$timescale
	1ps
$end
$scope module eight_bit_alu_tb $end
$scope module out $end
$var wire 8 ! a [7:0] $end
$var wire 8 " b [7:0] $end
$var wire 3 # sel [2:0] $end
$var wire 9 $ sum [8:0] $end
$var wire 8 % o [7:0] $end
$var wire 1 & c $end
$upscope $end
$upscope $end
$enddefinitions $end
#0
$dumpvars
1&
b11101111 %
b111101111 $
b0 #
b11110000 "
b11111111 !
$end
#100000
b100011010 $
b11010 %
b1 #
b1010 !
#200000
0&
b10000000 %
b101111101 $
b10 #
b10001101 !
#300000
b11111110 %
b100101110 $
b11 #
b111110 !
#400000
b11001110 %
b100 #
#500000
b11000001 %
b101 #
#600000
b1111100 %
b110 #
#700000
b1111000 %
b111 #
